{"asset": {                "version": "0.0",                "gltfUpAxis": "Y"            },            "geometricError":100.000000,"root": {                "transform": [-0.851973,-0.523585,0.000000,0.000000,0.270303,-0.439835,0.856435,0.000000,-0.447611,0.728349,0.518800,0.000000,-2857498.694258,4649697.356745,3289788.396013,1],                "boundingVolume": {                    "region": [2.121785,0.545404,2.121915,0.545488,0.000000,39.600000]},"geometricError": 100.000000,                        "refine": "REPLACE",                        "content": {                            "uri": "./tile/7/88/89.b3dm"}}}