{"asset": {                "version": "0.0",                "gltfUpAxis": "Y"            },            "geometricError":100.000000,"root": {                "transform": [-0.854709,-0.519108,0.000000,0.000000,0.268668,-0.442360,0.855649,0.000000,-0.443372,0.730009,0.520104,0.000000,-2830450.150632,4660320.634852,3298073.327126,1],                "boundingVolume": {                    "region": [2.116539,0.546935,2.116668,0.547010,0.000000,92.400000]},"geometricError": 100.000000,                        "refine": "REPLACE",                        "content": {                            "uri": "./tile/7/43/111.b3dm"}}}