{"asset": {                "version": "0.0",                "gltfUpAxis": "Y"            },            "geometricError":100.000000,"root": {                "transform": [-0.854722,-0.519086,0.000000,0.000000,0.266992,-0.439627,0.857580,0.000000,-0.444364,0.731685,0.516893,0.000000,-2836749.537626,4670963.857595,3277678.551703,1],                "boundingVolume": {                    "region": [2.116545,0.543188,2.116611,0.543247,0.000000,16.500000]},"geometricError": 100.000000,                        "refine": "REPLACE",                        "content": {                            "uri": "./tile/7/43/57.b3dm"}}}