{"asset": {                "version": "0.0",                "gltfUpAxis": "Y"            },            "geometricError":100.000000,"root": {                "transform": [-0.850194,-0.526469,0.000000,0.000000,0.270245,-0.436418,0.858200,0.000000,-0.451013,0.728340,0.515857,0.000000,-2879189.747237,4649595.108404,3271093.145038,1],                "boundingVolume": {                    "region": [2.125172,0.542000,2.125306,0.542015,0.000000,33.000000]},"geometricError": 100.000000,                        "refine": "REPLACE",                        "content": {                            "uri": "./tile/7/117/40.b3dm"}}}