{"asset": {                "version": "0.0",                "gltfUpAxis": "Y"            },            "geometricError":100.000000,"root": {                "transform": [-0.855099,-0.518465,0.000000,0.000000,0.268438,-0.442732,0.855529,0.000000,-0.442760,0.730239,0.520302,0.000000,-2826544.281517,4661793.648222,3299332.593263,1],                "boundingVolume": {                    "region": [2.115849,0.547202,2.115852,0.547207,0.000000,6.600000]},"geometricError": 100.000000,                        "refine": "REPLACE",                        "content": {                            "uri": "./tile/7/36/114.b3dm"}}}