{"asset": {                "version": "0.0",                "gltfUpAxis": "Y"            },            "geometricError":100.000000,"root": {                "transform": [-0.852092,-0.523392,0.000000,0.000000,0.270854,-0.440956,0.855685,0.000000,-0.447050,0.727805,0.520044,0.000000,-2853930.045884,4646248.247724,3297696.380168,1],                "boundingVolume": {                    "region": [2.121556,0.546865,2.121691,0.546941,0.000000,39.600000]},"geometricError": 100.000000,                        "refine": "REPLACE",                        "content": {                            "uri": "./tile/7/86/110.b3dm"}}}