{"asset": {                "version": "0.0",                "gltfUpAxis": "Y"            },            "geometricError":100.000000,"root": {                "transform": [-0.852093,-0.523390,0.000000,0.000000,0.269098,-0.438100,0.857703,0.000000,-0.448113,0.729540,0.516687,0.000000,-2860682.349561,4657271.984497,3276369.934352,1],                "boundingVolume": {                    "region": [2.121568,0.542973,2.121673,0.542981,0.000000,9.900000]},"geometricError": 100.000000,                        "refine": "REPLACE",                        "content": {                            "uri": "./tile/7/86/54.b3dm"}}}