{"asset": {                "version": "0.0",                "gltfUpAxis": "Y"            },            "geometricError":100.000000,"root": {                "transform": [-0.853979,-0.520307,0.000000,0.000000,0.268428,-0.440571,0.856646,0.000000,-0.444919,0.730245,0.518449,0.000000,-2840312.647397,4661799.666645,3287558.179213,1],                "boundingVolume": {                    "region": [2.117940,0.544993,2.118074,0.545079,0.000000,42.900000]},"geometricError": 100.000000,                        "refine": "REPLACE",                        "content": {                            "uri": "./tile/7/55/83.b3dm"}}}