{"asset": {                "version": "0.0",                "gltfUpAxis": "Y"            },            "geometricError":100.000000,"root": {                "transform": [-0.854574,-0.519330,0.000000,0.000000,0.268097,-0.441162,0.856446,0.000000,-0.443979,0.730581,0.518781,0.000000,-2834313.839286,4663948.415653,3289672.833038,1],                "boundingVolume": {                    "region": [2.116813,0.545406,2.116914,0.545444,0.000000,6.600000]},"geometricError": 100.000000,                        "refine": "REPLACE",                        "content": {                            "uri": "./tile/7/45/89.b3dm"}}}