{"asset": {                "version": "0.0",                "gltfUpAxis": "Y"            },            "geometricError":100.000000,"root": {                "transform": [-0.850840,-0.525425,0.000000,0.000000,0.271221,-0.439198,0.856472,0.000000,-0.449203,0.727411,0.518738,0.000000,-2867662.118977,4643713.549898,3289399.288414,1],                "boundingVolume": {                    "region": [2.123999,0.545361,2.124022,0.545388,0.000000,13.200000]},"geometricError": 100.000000,                        "refine": "REPLACE",                        "content": {                            "uri": "./tile/7/106/88.b3dm"}}}