{"asset": {                "version": "0.0",                "gltfUpAxis": "Y"            },            "geometricError":100.000000,"root": {                "transform": [-0.852702,-0.522398,0.000000,0.000000,0.269937,-0.440614,0.856150,0.000000,-0.446446,0.728726,0.519273,0.000000,-2850065.927639,4652117.679233,3292792.737446,1],                "boundingVolume": {                    "region": [2.120397,0.545962,2.120517,0.546037,0.000000,66.000000]},"geometricError": 100.000000,                        "refine": "REPLACE",                        "content": {                            "uri": "./tile/7/76/97.b3dm"}}}