{"asset": {                "version": "0.0",                "gltfUpAxis": "Y"            },            "geometricError":100.000000,"root": {                "transform": [-0.856339,-0.516414,0.000000,0.000000,0.266998,-0.442747,0.855971,0.000000,-0.441238,0.731680,0.519570,0.000000,-2816825.397754,4670979.822530,3294680.119299,1],                "boundingVolume": {                    "region": [2.113406,0.546308,2.113502,0.546386,0.000000,19.800000]},"geometricError": 100.000000,                        "refine": "REPLACE",                        "content": {                            "uri": "./tile/7/16/102.b3dm"}}}