{"asset": {                "version": "0.0",                "gltfUpAxis": "Y"            },            "geometricError":100.000000,"root": {                "transform": [-0.853733,-0.520710,0.000000,0.000000,0.268601,-0.440387,0.856687,0.000000,-0.445285,0.730070,0.518381,0.000000,-2842648.611190,4660679.672616,3287130.007092,1],                "boundingVolume": {                    "region": [2.118417,0.544920,2.118541,0.544994,0.000000,52.800000]},"geometricError": 100.000000,                        "refine": "REPLACE",                        "content": {                            "uri": "./tile/7/59/82.b3dm"}}}