{"asset": {                "version": "0.0",                "gltfUpAxis": "Y"            },            "geometricError":100.000000,"root": {                "transform": [-0.851673,-0.524074,0.000000,0.000000,0.271114,-0.440587,0.855792,0.000000,-0.447689,0.727539,0.519866,0.000000,-2858008.745326,4644549.010203,3296565.133647,1],                "boundingVolume": {                    "region": [2.122349,0.546658,2.122498,0.546731,0.000000,36.300000]},"geometricError": 100.000000,                        "refine": "REPLACE",                        "content": {                            "uri": "./tile/7/93/107.b3dm"}}}