{"asset": {                "version": "0.0",                "gltfUpAxis": "Y"            },            "geometricError":100.000000,"root": {                "transform": [-0.851421,-0.524483,0.000000,0.000000,0.270175,-0.438589,0.857115,0.000000,-0.448737,0.728459,0.517669,0.000000,-2864679.030862,4650387.654113,3282608.525850,1],                "boundingVolume": {                    "region": [2.122845,0.544083,2.122963,0.544166,0.000000,19.800000]},"geometricError": 100.000000,                        "refine": "REPLACE",                        "content": {                            "uri": "./tile/7/97/70.b3dm"}}}