{"asset": {                "version": "0.0",                "gltfUpAxis": "Y"            },            "geometricError":100.000000,"root": {                "transform": [-0.853372,-0.521303,0.000000,0.000000,0.269062,-0.440455,0.856508,0.000000,-0.445698,0.729606,0.518679,0.000000,-2845283.989669,4657724.843127,3289024.801905,1],                "boundingVolume": {                    "region": [2.119110,0.545265,2.119236,0.545346,0.000000,95.700000]},"geometricError": 100.000000,                        "refine": "REPLACE",                        "content": {                            "uri": "./tile/7/65/87.b3dm"}}}