{"asset": {                "version": "0.0",                "gltfUpAxis": "Y"            },            "geometricError":100.000000,"root": {                "transform": [-0.853371,-0.521304,0.000000,0.000000,0.269155,-0.440605,0.856401,0.000000,-0.445643,0.729514,0.518856,0.000000,-2844936.067454,4657138.801333,3290147.869587,1],                "boundingVolume": {                    "region": [2.119114,0.545474,2.119236,0.545550,0.000000,39.600000]},"geometricError": 100.000000,                        "refine": "REPLACE",                        "content": {                            "uri": "./tile/7/65/90.b3dm"}}}