{"asset": {                "version": "0.0",                "gltfUpAxis": "Y"            },            "geometricError":100.000000,"root": {                "transform": [-0.853369,-0.521308,0.000000,0.000000,0.269346,-0.440913,0.856182,0.000000,-0.445531,0.729324,0.519220,0.000000,-2844225.723913,4655929.234140,3292457.528987,1],                "boundingVolume": {                    "region": [2.119114,0.545891,2.119244,0.545984,0.000000,66.000000]},"geometricError": 100.000000,                        "refine": "REPLACE",                        "content": {                            "uri": "./tile/7/65/96.b3dm"}}}