{"asset": {                "version": "0.0",                "gltfUpAxis": "Y"            },            "geometricError":100.000000,"root": {                "transform": [-0.854521,-0.519417,0.000000,0.000000,0.268126,-0.441108,0.856465,0.000000,-0.444063,0.730552,0.518750,0.000000,-2834850.507464,4663762.934063,3289474.698545,1],                "boundingVolume": {                    "region": [2.116902,0.545364,2.117028,0.545413,0.000000,6.600000]},"geometricError": 100.000000,                        "refine": "REPLACE",                        "content": {                            "uri": "./tile/7/46/88.b3dm"}}}