{"asset": {                "version": "0.0",                "gltfUpAxis": "Y"            },            "geometricError":100.000000,"root": {                "transform": [-0.854545,-0.519378,0.000000,0.000000,0.268197,-0.441270,0.856359,0.000000,-0.443974,0.730481,0.518926,0.000000,-2834283.582516,4663315.429070,3290589.950561,1],                "boundingVolume": {                    "region": [2.116909,0.545583,2.116929,0.545605,0.000000,6.600000]},"geometricError": 100.000000,                        "refine": "REPLACE",                        "content": {                            "uri": "./tile/7/46/91.b3dm"}}}