{"asset": {                "version": "0.0",                "gltfUpAxis": "Y"            },            "geometricError":100.000000,"root": {                "transform": [-0.854523,-0.519414,0.000000,0.000000,0.268302,-0.441402,0.856258,0.000000,-0.443952,0.730376,0.519093,0.000000,-2834143.911948,4662644.037475,3291654.309007,1],                "boundingVolume": {                    "region": [2.116896,0.545753,2.117026,0.545827,0.000000,16.500000]},"geometricError": 100.000000,                        "refine": "REPLACE",                        "content": {                            "uri": "./tile/7/46/94.b3dm"}}}