{"asset": {                "version": "0.0",                "gltfUpAxis": "Y"            },            "geometricError":100.000000,"root": {                "transform": [-0.855069,-0.518515,0.000000,0.000000,0.266169,-0.438932,0.858191,0.000000,-0.444194,0.732508,0.515871,0.000000,-2835658.124458,4676206.793375,3271184.439566,1],                "boundingVolume": {                    "region": [2.115899,0.541999,2.115920,0.542049,0.000000,49.500000]},"geometricError": 100.000000,                        "refine": "REPLACE",                        "content": {                            "uri": "./tile/7/37/40.b3dm"}}}