{"asset": {                "version": "0.0",                "gltfUpAxis": "Y"            },            "geometricError":100.000000,"root": {                "transform": [-0.849885,-0.526968,0.000000,0.000000,0.269406,-0.434492,0.859440,0.000000,-0.452099,0.729138,0.513775,0.000000,-2886102.267866,4654653.469101,3257869.744674,1],                "boundingVolume": {                    "region": [2.125782,0.539566,2.125870,0.539593,0.000000,49.500000]},"geometricError": 100.000000,                        "refine": "REPLACE",                        "content": {                            "uri": "./tile/7/122/5.b3dm"}}}