{"asset": {                "version": "0.0",                "gltfUpAxis": "Y"            },            "geometricError":100.000000,"root": {                "transform": [-0.855248,-0.518219,0.000000,0.000000,0.266700,-0.440151,0.857402,0.000000,-0.443528,0.731982,0.517190,0.000000,-2831417.533618,4672864.576419,3279566.428234,1],                "boundingVolume": {                    "region": [2.115499,0.543527,2.115627,0.543603,0.000000,9.900000]},"geometricError": 100.000000,                        "refine": "REPLACE",                        "content": {                            "uri": "./tile/7/34/62.b3dm"}}}