{"asset": {                "version": "0.0",                "gltfUpAxis": "Y"            },            "geometricError":100.000000,"root": {                "transform": [-0.854279,-0.519814,0.000000,0.000000,0.267398,-0.439450,0.857544,0.000000,-0.444968,0.731275,0.516953,0.000000,-2840611.857832,4668349.291749,3278055.899119,1],                "boundingVolume": {                    "region": [2.117363,0.543249,2.117497,0.543325,0.000000,56.100000]},"geometricError": 100.000000,                        "refine": "REPLACE",                        "content": {                            "uri": "./tile/7/50/58.b3dm"}}}