{"asset": {                "version": "0.0",                "gltfUpAxis": "Y"            },            "geometricError":100.000000,"root": {                "transform": [-0.850909,-0.525313,0.000000,0.000000,0.270842,-0.438714,0.856840,0.000000,-0.449302,0.727786,0.518126,0.000000,-2868288.378015,4646097.650403,3285510.608380,1],                "boundingVolume": {                    "region": [2.123864,0.544651,2.123893,0.544666,0.000000,6.600000]},"geometricError": 100.000000,                        "refine": "REPLACE",                        "content": {                            "uri": "./tile/7/105/78.b3dm"}}}