{"asset": {                "version": "0.0",                "gltfUpAxis": "Y"            },            "geometricError":100.000000,"root": {                "transform": [-0.855188,-0.518318,0.000000,0.000000,0.265887,-0.438695,0.858400,0.000000,-0.444135,0.732791,0.515521,0.000000,-2835276.211255,4678003.261939,3268961.133960,1],                "boundingVolume": {                    "region": [2.115620,0.541581,2.115739,0.541650,0.000000,29.700000]},"geometricError": 100.000000,                        "refine": "REPLACE",                        "content": {                            "uri": "./tile/7/35/34.b3dm"}}}