{"asset": {                "version": "0.0",                "gltfUpAxis": "Y"            },            "geometricError":100.000000,"root": {                "transform": [-0.855183,-0.518326,0.000000,0.000000,0.266698,-0.440023,0.857468,0.000000,-0.443654,0.731983,0.517080,0.000000,-2832224.784268,4672872.410173,3278862.891725,1],                "boundingVolume": {                    "region": [2.115637,0.543390,2.115740,0.543482,0.000000,52.800000]},"geometricError": 100.000000,                        "refine": "REPLACE",                        "content": {                            "uri": "./tile/7/35/60.b3dm"}}}