{"asset": {                "version": "0.0",                "gltfUpAxis": "Y"            },            "geometricError":100.000000,"root": {                "transform": [-0.851056,-0.525075,0.000000,0.000000,0.271032,-0.439296,0.856481,0.000000,-0.448909,0.727604,0.518723,0.000000,-2865784.857540,4644941.342738,3289302.449928,1],                "boundingVolume": {                    "region": [2.123564,0.545336,2.123635,0.545377,0.000000,16.500000]},"geometricError": 100.000000,                        "refine": "REPLACE",                        "content": {                            "uri": "./tile/7/103/88.b3dm"}}}