{"asset": {                "version": "0.0",                "gltfUpAxis": "Y"            },            "geometricError":100.000000,"root": {                "transform": [-0.854949,-0.518713,0.000000,0.000000,0.265937,-0.438320,0.858576,0.000000,-0.444565,0.732737,0.515226,0.000000,-2838020.112494,4677657.736276,3267086.641379,1],                "boundingVolume": {                    "region": [2.116075,0.541233,2.116207,0.541309,0.000000,23.100000]},"geometricError": 100.000000,                        "refine": "REPLACE",                        "content": {                            "uri": "./tile/7/39/29.b3dm"}}}