{"asset": {                "version": "0.0",                "gltfUpAxis": "Y"            },            "geometricError":100.000000,"root": {                "transform": [-0.855348,-0.518055,0.000000,0.000000,0.267429,-0.441546,0.856457,0.000000,-0.442894,0.731252,0.518764,0.000000,-2827386.388699,4668230.594179,3289560.973802,1],                "boundingVolume": {                    "region": [2.115370,0.545402,2.115373,0.545406,0.000000,3.300000]},"geometricError": 100.000000,                        "refine": "REPLACE",                        "content": {                            "uri": "./tile/7/32/88.b3dm"}}}