{"asset": {                "version": "0.0",                "gltfUpAxis": "Y"            },            "geometricError":100.000000,"root": {                "transform": [-0.855487,-0.517825,0.000000,0.000000,0.267664,-0.442202,0.856045,0.000000,-0.442483,0.731016,0.519447,0.000000,-2824769.272579,4666734.771333,3293899.619030,1],                "boundingVolume": {                    "region": [2.115056,0.546172,2.115150,0.546235,0.000000,52.800000]},"geometricError": 100.000000,                        "refine": "REPLACE",                        "content": {                            "uri": "./tile/7/30/100.b3dm"}}}