{"asset": {                "version": "0.0",                "gltfUpAxis": "Y"            },            "geometricError":100.000000,"root": {                "transform": [-0.855506,-0.517793,0.000000,0.000000,0.266912,-0.440997,0.856901,0.000000,-0.442902,0.731770,0.518025,0.000000,-2827429.336803,4671529.513542,3284869.146316,1],                "boundingVolume": {                    "region": [2.115038,0.544501,2.115092,0.544580,0.000000,19.800000]},"geometricError": 100.000000,                        "refine": "REPLACE",                        "content": {                            "uri": "./tile/7/30/76.b3dm"}}}