{"asset": {                "version": "0.0",                "gltfUpAxis": "Y"            },            "geometricError":100.000000,"root": {                "transform": [-0.852477,-0.522764,0.000000,0.000000,0.268515,-0.437869,0.858004,0.000000,-0.447736,0.730127,0.516185,0.000000,-2858270.247858,4661009.134314,3273180.655929,1],                "boundingVolume": {                    "region": [2.120864,0.542357,2.120910,0.542425,0.000000,39.600000]},"geometricError": 100.000000,                        "refine": "REPLACE",                        "content": {                            "uri": "./tile/7/80/45.b3dm"}}}