{"asset": {                "version": "0.0",                "gltfUpAxis": "Y"            },            "geometricError":100.000000,"root": {                "transform": [-0.851785,-0.523891,0.000000,0.000000,0.270181,-0.439283,0.856757,0.000000,-0.448042,0.728464,0.518265,0.000000,-2860247.481577,4650426.731757,3286389.838221,1],                "boundingVolume": {                    "region": [2.122144,0.544781,2.122274,0.544860,0.000000,29.700000]},"geometricError": 100.000000,                        "refine": "REPLACE",                        "content": {                            "uri": "./tile/7/91/80.b3dm"}}}