{"asset": {                "version": "0.0",                "gltfUpAxis": "Y"            },            "geometricError":100.000000,"root": {                "transform": [-0.854886,-0.518816,0.000000,0.000000,0.266731,-0.439510,0.857721,0.000000,-0.444206,0.731947,0.516657,0.000000,-2835743.485173,4672632.596674,3276180.346768,1],                "boundingVolume": {                    "region": [2.116205,0.542907,2.116318,0.542977,0.000000,66.000000]},"geometricError": 100.000000,                        "refine": "REPLACE",                        "content": {                            "uri": "./tile/7/40/53.b3dm"}}}