{"asset": {                "version": "0.0",                "gltfUpAxis": "Y"            },            "geometricError":100.000000,"root": {                "transform": [-0.852216,-0.523189,0.000000,0.000000,0.270594,-0.440767,0.855864,0.000000,-0.446971,0.728066,0.519747,0.000000,-2853425.593576,4647907.273176,3295807.217130,1],                "boundingVolume": {                    "region": [2.121328,0.546517,2.121443,0.546592,0.000000,29.700000]},"geometricError": 100.000000,                        "refine": "REPLACE",                        "content": {                            "uri": "./tile/7/84/105.b3dm"}}}