{"asset": {                "version": "0.0",                "gltfUpAxis": "Y"            },            "geometricError":100.000000,"root": {                "transform": [-0.856944,-0.515409,0.000000,0.000000,0.266542,-0.443166,0.855897,0.000000,-0.440342,0.732133,0.519693,0.000000,-2811101.529056,4673871.678097,3295462.319855,1],                "boundingVolume": {                    "region": [2.112242,0.546461,2.112321,0.546522,0.000000,33.000000]},"geometricError": 100.000000,                        "refine": "REPLACE",                        "content": {                            "uri": "./tile/7/6/104.b3dm"}}}