{"asset": {                "version": "0.0",                "gltfUpAxis": "Y"            },            "geometricError":100.000000,"root": {                "transform": [-0.852175,-0.523257,0.000000,0.000000,0.270756,-0.440952,0.855717,0.000000,-0.446952,0.727904,0.519990,0.000000,-2853303.520244,4646879.161888,3297351.860388,1],                "boundingVolume": {                    "region": [2.121437,0.546795,2.121493,0.546883,0.000000,26.400000]},"geometricError": 100.000000,                        "refine": "REPLACE",                        "content": {                            "uri": "./tile/7/85/109.b3dm"}}}