{"asset": {                "version": "0.0",                "gltfUpAxis": "Y"            },            "geometricError":100.000000,"root": {                "transform": [-0.852379,-0.522925,0.000000,0.000000,0.268840,-0.438216,0.857725,0.000000,-0.447726,0.729803,0.516651,0.000000,-2858213.678872,4658949.172702,3276141.488065,1],                "boundingVolume": {                    "region": [2.121061,0.542903,2.121089,0.542968,0.000000,16.500000]},"geometricError": 100.000000,                        "refine": "REPLACE",                        "content": {                            "uri": "./tile/7/81/53.b3dm"}}}