{"asset": {                "version": "0.0",                "gltfUpAxis": "Y"            },            "geometricError":100.000000,"root": {                "transform": [-0.851489,-0.524372,0.000000,0.000000,0.269744,-0.438018,0.857542,0.000000,-0.448869,0.728885,0.516956,0.000000,-2865510.828503,4653090.424411,3278079.841989,1],                "boundingVolume": {                    "region": [2.122715,0.543253,2.122833,0.543330,0.000000,16.500000]},"geometricError": 100.000000,                        "refine": "REPLACE",                        "content": {                            "uri": "./tile/7/96/58.b3dm"}}}