{"asset": {                "version": "0.0",                "gltfUpAxis": "Y"            },            "geometricError":100.000000,"root": {                "transform": [-0.854159,-0.520012,0.000000,0.000000,0.269531,-0.442725,0.855189,0.000000,-0.443903,0.729144,0.520864,0.000000,-2833848.086311,4654807.877886,3302904.459073,1],                "boundingVolume": {                    "region": [2.117609,0.547840,2.117714,0.547886,0.000000,72.600000]},"geometricError": 100.000000,                        "refine": "REPLACE",                        "content": {                            "uri": "./tile/7/52/124.b3dm"}}}