{"asset": {                "version": "0.0",                "gltfUpAxis": "Y"            },            "geometricError":100.000000,"root": {                "transform": [-0.853792,-0.520614,0.000000,0.000000,0.269354,-0.441734,0.855757,0.000000,-0.444715,0.729319,0.519925,0.000000,-2839020.312617,4655913.834909,3296938.671632,1],                "boundingVolume": {                    "region": [2.118301,0.546726,2.118431,0.546801,0.000000,42.900000]},"geometricError": 100.000000,                        "refine": "REPLACE",                        "content": {                            "uri": "./tile/7/58/108.b3dm"}}}