{"asset": {                "version": "0.0",                "gltfUpAxis": "Y"            },            "geometricError":100.000000,"root": {                "transform": [-0.854400,-0.519616,0.000000,0.000000,0.267730,-0.440226,0.857042,0.000000,-0.444536,0.730946,0.517790,0.000000,-2837858.144446,4666260.723506,3283374.504074,1],                "boundingVolume": {                    "region": [2.117134,0.544223,2.117263,0.544309,0.000000,9.900000]},"geometricError": 100.000000,                        "refine": "REPLACE",                        "content": {                            "uri": "./tile/7/48/72.b3dm"}}}