{"asset": {                "version": "0.0",                "gltfUpAxis": "Y"            },            "geometricError":100.000000,"root": {                "transform": [-0.854415,-0.519591,0.000000,0.000000,0.267962,-0.440636,0.856759,0.000000,-0.444366,0.730715,0.518261,0.000000,-2836780.589170,4664794.661468,3286367.335544,1],                "boundingVolume": {                    "region": [2.117130,0.544779,2.117208,0.544854,0.000000,66.000000]},"geometricError": 100.000000,                        "refine": "REPLACE",                        "content": {                            "uri": "./tile/7/48/80.b3dm"}}}