{"asset": {                "version": "0.0",                "gltfUpAxis": "Y"            },            "geometricError":100.000000,"root": {                "transform": [-0.854402,-0.519613,0.000000,0.000000,0.268252,-0.441087,0.856437,0.000000,-0.444216,0.730425,0.518797,0.000000,-2835826.446283,4662956.367247,3289774.896535,1],                "boundingVolume": {                    "region": [2.117138,0.545405,2.117251,0.545483,0.000000,49.500000]},"geometricError": 100.000000,                        "refine": "REPLACE",                        "content": {                            "uri": "./tile/7/48/89.b3dm"}}}