{"asset": {                "version": "0.0",                "gltfUpAxis": "Y"            },            "geometricError":100.000000,"root": {                "transform": [-0.852516,-0.522702,0.000000,0.000000,0.269133,-0.438950,0.857258,0.000000,-0.447289,0.729519,0.517431,0.000000,-2855430.528230,4657146.442049,3281094.407625,1],                "boundingVolume": {                    "region": [2.120745,0.543806,2.120882,0.543886,0.000000,33.000000]},"geometricError": 100.000000,                        "refine": "REPLACE",                        "content": {                            "uri": "./tile/7/79/66.b3dm"}}}