{"asset": {                "version": "0.0",                "gltfUpAxis": "Y"            },            "geometricError":100.000000,"root": {                "transform": [-0.852519,-0.522696,0.000000,0.000000,0.269532,-0.439608,0.856795,0.000000,-0.447040,0.729124,0.518202,0.000000,-2853847.529527,4654638.977471,3285993.069739,1],                "boundingVolume": {                    "region": [2.120737,0.544709,2.120875,0.544786,0.000000,89.100000]},"geometricError": 100.000000,                        "refine": "REPLACE",                        "content": {                            "uri": "./tile/7/79/79.b3dm"}}}