{"asset": {                "version": "0.0",                "gltfUpAxis": "Y"            },            "geometricError":100.000000,"root": {                "transform": [-0.852523,-0.522690,0.000000,0.000000,0.269717,-0.439916,0.856579,0.000000,-0.446921,0.728941,0.518561,0.000000,-2853095.376306,4653478.320289,3288273.927839,1],                "boundingVolume": {                    "region": [2.120735,0.545128,2.120865,0.545206,0.000000,125.400000]},"geometricError": 100.000000,                        "refine": "REPLACE",                        "content": {                            "uri": "./tile/7/79/85.b3dm"}}}