{"asset": {                "version": "0.0",                "gltfUpAxis": "Y"            },            "geometricError":100.000000,"root": {                "transform": [-0.854043,-0.520202,0.000000,0.000000,0.266917,-0.438211,0.858327,0.000000,-0.445711,0.731747,0.515643,0.000000,-2845340.801522,4671341.165569,3269737.881978,1],                "boundingVolume": {                    "region": [2.117835,0.541719,2.117933,0.541797,0.000000,16.500000]},"geometricError": 100.000000,                        "refine": "REPLACE",                        "content": {                            "uri": "./tile/7/54/36.b3dm"}}}