{"asset": {                "version": "0.0",                "gltfUpAxis": "Y"            },            "geometricError":100.000000,"root": {                "transform": [-0.853002,-0.521907,0.000000,0.000000,0.267851,-0.437774,0.858260,0.000000,-0.447136,0.730797,0.515757,0.000000,-2854439.235918,4665278.630701,3270458.463827,1],                "boundingVolume": {                    "region": [2.119826,0.541859,2.119938,0.541922,0.000000,26.400000]},"geometricError": 100.000000,                        "refine": "REPLACE",                        "content": {                            "uri": "./tile/7/71/38.b3dm"}}}