{"asset": {                "version": "0.0",                "gltfUpAxis": "Y"            },            "geometricError":100.000000,"root": {                "transform": [-0.853004,-0.521904,0.000000,0.000000,0.266858,-0.436154,0.859393,0.000000,-0.447730,0.731773,0.513854,0.000000,-2858211.081372,4671478.745709,3258372.927718,1],                "boundingVolume": {                    "region": [2.119813,0.539635,2.119944,0.539708,0.000000,19.800000]},"geometricError": 100.000000,                        "refine": "REPLACE",                        "content": {                            "uri": "./tile/7/71/6.b3dm"}}}