{"asset": {                "version": "0.0",                "gltfUpAxis": "Y"            },            "geometricError":100.000000,"root": {                "transform": [-0.853857,-0.520508,0.000000,0.000000,0.267508,-0.438827,0.857829,0.000000,-0.445712,0.731158,0.516478,0.000000,-2845351.595390,4667595.206951,3275037.996931,1],                "boundingVolume": {                    "region": [2.118182,0.542693,2.118303,0.542772,0.000000,46.200000]},"geometricError": 100.000000,                        "refine": "REPLACE",                        "content": {                            "uri": "./tile/7/57/50.b3dm"}}}