{"asset": {                "version": "0.0",                "gltfUpAxis": "Y"            },            "geometricError":100.000000,"root": {                "transform": [-0.853856,-0.520509,0.000000,0.000000,0.267631,-0.439029,0.857687,0.000000,-0.445637,0.731036,0.516715,0.000000,-2844879.634821,4666818.316990,3276544.633253,1],                "boundingVolume": {                    "region": [2.118183,0.542971,2.118303,0.543048,0.000000,49.500000]},"geometricError": 100.000000,                        "refine": "REPLACE",                        "content": {                            "uri": "./tile/7/57/54.b3dm"}}}