{"asset": {                "version": "0.0",                "gltfUpAxis": "Y"            },            "geometricError":100.000000,"root": {                "transform": [-0.852730,-0.522351,0.000000,0.000000,0.268381,-0.438127,0.857914,0.000000,-0.447335,0.730267,0.516335,0.000000,-2855711.749043,4661904.498816,3274132.164516,1],                "boundingVolume": {                    "region": [2.120393,0.542556,2.120412,0.542576,0.000000,13.200000]},"geometricError": 100.000000,                        "refine": "REPLACE",                        "content": {                            "uri": "./tile/7/75/48.b3dm"}}}