{"asset": {                "version": "0.0",                "gltfUpAxis": "Y"            },            "geometricError":100.000000,"root": {                "transform": [-0.852762,-0.522300,0.000000,0.000000,0.269452,-0.439936,0.856651,0.000000,-0.446626,0.729208,0.518441,0.000000,-2851207.189672,4655180.514525,3287507.420012,1],                "boundingVolume": {                    "region": [2.120274,0.544987,2.120410,0.545065,0.000000,66.000000]},"geometricError": 100.000000,                        "refine": "REPLACE",                        "content": {                            "uri": "./tile/7/75/83.b3dm"}}}