{"asset": {                "version": "0.0",                "gltfUpAxis": "Y"            },            "geometricError":100.000000,"root": {                "transform": [-0.852761,-0.522301,0.000000,0.000000,0.269673,-0.440295,0.856397,0.000000,-0.446493,0.728989,0.518863,0.000000,-2850364.970846,4653789.189884,3290188.437839,1],                "boundingVolume": {                    "region": [2.120279,0.545474,2.120409,0.545566,0.000000,89.100000]},"geometricError": 100.000000,                        "refine": "REPLACE",                        "content": {                            "uri": "./tile/7/75/90.b3dm"}}}