{"asset": {                "version": "0.0",                "gltfUpAxis": "Y"            },            "geometricError":100.000000,"root": {                "transform": [-0.856390,-0.516329,0.000000,0.000000,0.265931,-0.441077,0.857165,0.000000,-0.441787,0.732754,0.517586,0.000000,-2820311.087735,4677803.205115,3282078.005112,1],                "boundingVolume": {                    "region": [2.113325,0.544018,2.113386,0.544036,0.000000,16.500000]},"geometricError": 100.000000,                        "refine": "REPLACE",                        "content": {                            "uri": "./tile/7/15/69.b3dm"}}}