{"asset": {                "version": "0.0",                "gltfUpAxis": "Y"            },            "geometricError":100.000000,"root": {                "transform": [-0.851295,-0.524688,0.000000,0.000000,0.270342,-0.438625,0.857043,0.000000,-0.448875,0.728290,0.517788,0.000000,-2865557.620482,4649308.585465,3283365.003017,1],                "boundingVolume": {                    "region": [2.123091,0.544224,2.123197,0.544303,0.000000,19.800000]},"geometricError": 100.000000,                        "refine": "REPLACE",                        "content": {                            "uri": "./tile/7/99/72.b3dm"}}}