{"asset": {                "version": "0.0",                "gltfUpAxis": "Y"            },            "geometricError":100.000000,"root": {                "transform": [-0.855525,-0.517761,0.000000,0.000000,0.265774,-0.439153,0.858201,0.000000,-0.443553,0.732908,0.515855,0.000000,-2831567.503345,4678755.744842,3271083.796314,1],                "boundingVolume": {                    "region": [2.115021,0.542004,2.115035,0.542007,0.000000,33.000000]},"geometricError": 100.000000,                        "refine": "REPLACE",                        "content": {                            "uri": "./tile/7/29/40.b3dm"}}}