{"asset": {                "version": "0.0",                "gltfUpAxis": "Y"            },            "geometricError":100.000000,"root": {                "transform": [-0.855793,-0.517319,0.000000,0.000000,0.267496,-0.442515,0.855936,0.000000,-0.441993,0.731183,0.519628,0.000000,-2821645.286527,4667807.229204,3295049.627852,1],                "boundingVolume": {                    "region": [2.114449,0.546378,2.114574,0.546452,0.000000,36.300000]},"geometricError": 100.000000,                        "refine": "REPLACE",                        "content": {                            "uri": "./tile/7/25/103.b3dm"}}}