{"asset": {                "version": "0.0",                "gltfUpAxis": "Y"            },            "geometricError":100.000000,"root": {                "transform": [-0.851740,-0.523965,0.000000,0.000000,0.269501,-0.438092,0.857580,0.000000,-0.448540,0.729132,0.516893,0.000000,-2863414.207746,4654668.637441,3277674.043609,1],                "boundingVolume": {                    "region": [2.122261,0.543180,2.122331,0.543254,0.000000,49.500000]},"geometricError": 100.000000,                        "refine": "REPLACE",                        "content": {                            "uri": "./tile/7/92/57.b3dm"}}}