{"asset": {                "version": "0.0",                "gltfUpAxis": "Y"            },            "geometricError":100.000000,"root": {                "transform": [-0.852030,-0.523494,0.000000,0.000000,0.270162,-0.439711,0.856543,0.000000,-0.447590,0.728489,0.518620,0.000000,-2857361.516845,4650594.065490,3288647.528753,1],                "boundingVolume": {                    "region": [2.121678,0.545199,2.121807,0.545273,0.000000,66.000000]},"geometricError": 100.000000,                        "refine": "REPLACE",                        "content": {                            "uri": "./tile/7/87/86.b3dm"}}}