{"asset": {                "version": "0.0",                "gltfUpAxis": "Y"            },            "geometricError":100.000000,"root": {                "transform": [-0.852026,-0.523500,0.000000,0.000000,0.270443,-0.440160,0.856224,0.000000,-0.447427,0.728212,0.519150,0.000000,-2856326.429917,4648830.696616,3292015.443468,1],                "boundingVolume": {                    "region": [2.121702,0.545824,2.121798,0.545889,0.000000,36.300000]},"geometricError": 100.000000,                        "refine": "REPLACE",                        "content": {                            "uri": "./tile/7/87/95.b3dm"}}}