{"asset": {                "version": "0.0",                "gltfUpAxis": "Y"            },            "geometricError":100.000000,"root": {                "transform": [-0.851545,-0.524282,0.000000,0.000000,0.271433,-0.440864,0.855548,0.000000,-0.447738,0.727221,0.520270,0.000000,-2858324.942632,4642520.956715,3299129.412323,1],                "boundingVolume": {                    "region": [2.122611,0.547146,2.122726,0.547188,0.000000,23.100000]},"geometricError": 100.000000,                        "refine": "REPLACE",                        "content": {                            "uri": "./tile/7/95/114.b3dm"}}}