{"asset": {                "version": "0.0",                "gltfUpAxis": "Y"            },            "geometricError":100.000000,"root": {                "transform": [-0.853187,-0.521605,0.000000,0.000000,0.269930,-0.441523,0.855684,0.000000,-0.445523,0.728740,0.520045,0.000000,-2844184.566060,4652216.466791,3297701.739716,1],                "boundingVolume": {                    "region": [2.119460,0.546865,2.119595,0.546943,0.000000,46.200000]},"geometricError": 100.000000,                        "refine": "REPLACE",                        "content": {                            "uri": "./tile/7/68/110.b3dm"}}}