{"asset": {                "version": "0.0",                "gltfUpAxis": "Y"            },            "geometricError":100.000000,"root": {                "transform": [-0.853186,-0.521607,0.000000,0.000000,0.267265,-0.437162,0.858754,0.000000,-0.447139,0.731380,0.514928,0.000000,-2854447.155137,4668984.681215,3265194.019562,1],                "boundingVolume": {                    "region": [2.119464,0.540885,2.119595,0.540962,0.000000,66.000000]},"geometricError": 100.000000,                        "refine": "REPLACE",                        "content": {                            "uri": "./tile/7/68/24.b3dm"}}}