{"asset": {                "version": "0.0",                "gltfUpAxis": "Y"            },            "geometricError":100.000000,"root": {                "transform": [-0.853201,-0.521582,0.000000,0.000000,0.267729,-0.437949,0.858208,0.000000,-0.446831,0.730923,0.515843,0.000000,-2852490.856209,4666083.886552,3271005.894526,1],                "boundingVolume": {                    "region": [2.119478,0.541977,2.119524,0.542005,0.000000,9.900000]},"geometricError": 100.000000,                        "refine": "REPLACE",                        "content": {                            "uri": "./tile/7/68/39.b3dm"}}}