{"asset": {                "version": "0.0",                "gltfUpAxis": "Y"            },            "geometricError":100.000000,"root": {                "transform": [-0.852591,-0.522580,0.000000,0.000000,0.268109,-0.437420,0.858360,0.000000,-0.447765,0.730530,0.515589,0.000000,-2858450.473530,4663573.345018,3269394.144709,1],                "boundingVolume": {                    "region": [2.120626,0.541666,2.120714,0.541725,0.000000,66.000000]},"geometricError": 100.000000,                        "refine": "REPLACE",                        "content": {                            "uri": "./tile/7/78/35.b3dm"}}}