{"asset": {                "version": "0.0",                "gltfUpAxis": "Y"            },            "geometricError":100.000000,"root": {                "transform": [-0.852585,-0.522589,0.000000,0.000000,0.269074,-0.438984,0.857259,0.000000,-0.447193,0.729579,0.517429,0.000000,-2854819.120412,4657529.846996,3281082.297904,1],                "boundingVolume": {                    "region": [2.120611,0.543806,2.120751,0.543881,0.000000,39.600000]},"geometricError": 100.000000,                        "refine": "REPLACE",                        "content": {                            "uri": "./tile/7/78/66.b3dm"}}}