{"asset": {                "version": "0.0",                "gltfUpAxis": "Y"            },            "geometricError":100.000000,"root": {                "transform": [-0.853309,-0.521406,0.000000,0.000000,0.268154,-0.438848,0.857616,0.000000,-0.446368,0.730506,0.516833,0.000000,-2849547.964124,4663439.016337,3277294.296045,1],                "boundingVolume": {                    "region": [2.119235,0.543110,2.119353,0.543184,0.000000,19.800000]},"geometricError": 100.000000,                        "refine": "REPLACE",                        "content": {                            "uri": "./tile/7/66/56.b3dm"}}}