{"asset": {                "version": "0.0",                "gltfUpAxis": "Y"            },            "geometricError":100.000000,"root": {                "transform": [-0.853312,-0.521400,0.000000,0.000000,0.268369,-0.439207,0.857366,0.000000,-0.446232,0.730293,0.517251,0.000000,-2848680.700250,4662087.900532,3279951.555515,1],                "boundingVolume": {                    "region": [2.119223,0.543597,2.119352,0.543675,0.000000,59.400000]},"geometricError": 100.000000,                        "refine": "REPLACE",                        "content": {                            "uri": "./tile/7/66/63.b3dm"}}}