{"asset": {                "version": "0.0",                "gltfUpAxis": "Y"            },            "geometricError":100.000000,"root": {                "transform": [-0.853247,-0.521507,0.000000,0.000000,0.267490,-0.437645,0.858438,0.000000,-0.446887,0.731160,0.515458,0.000000,-2852844.970793,4667591.502541,3268561.663287,1],                "boundingVolume": {                    "region": [2.119342,0.541512,2.119483,0.541573,0.000000,19.800000]},"geometricError": 100.000000,                        "refine": "REPLACE",                        "content": {                            "uri": "./tile/7/67/33.b3dm"}}}